datastructures_algorithms/__init__.py
datastructures_algorithms/double_linked_list.py
datastructures_algorithms/linked_list.py
datastructures_algorithms/queue.py
datastructures_algorithms/searching.py
datastructures_algorithms/sorting.py
datastructures_algorithms/stack.py
datastructures_algorithms/strings.py
datastructures_algorithms/trie.py
datastructuresalgorithms_bharadwaj-0.0.2.dist-info/LICENSE
datastructuresalgorithms_bharadwaj-0.0.2.dist-info/METADATA
datastructuresalgorithms_bharadwaj-0.0.2.dist-info/WHEEL
datastructuresalgorithms_bharadwaj-0.0.2.dist-info/top_level.txt
datastructuresalgorithms_bharadwaj-0.0.2.dist-info/RECORD
