Metadata-Version: 2.1
Name: datastructuresalgorithms-bharadwaj
Version: 0.0.2
Summary: Data Structures and Algorithms
Home-page: https://github.com/bharadwajvyadavalli/datastructuresalgorithms
Author: Bharadwaj Yadavalli
Author-email: educationyvb@pm.me
License: UNKNOWN
Project-URL: Bug Tracker, https://github.com/bharadwajvyadavalli/datastructuresalgorithms
Platform: UNKNOWN
Classifier: Programming Language :: Python :: 3
Classifier: License :: OSI Approved :: MIT License
Classifier: Operating System :: OS Independent
Requires-Python: >=3.6
License-File: LICENSE
